graphicle/__init__.py
graphicle/_version.py
graphicle/matrices.py
graphicle-0.0.1.dist-info/LICENSE.txt
graphicle-0.0.1.dist-info/METADATA
graphicle-0.0.1.dist-info/WHEEL
graphicle-0.0.1.dist-info/top_level.txt
graphicle-0.0.1.dist-info/RECORD
