Metadata-Version: 2.1
Name: graphicle
Version: 0.0.1
Summary: Encode particle physics data onto graph structures.
Home-page: https://github.com/jacanchaplais/graphicle
Author: Jacan Chaplais
Author-email: jacanchaplais@gmail.com
License: BSD 3-Clause License
Platform: UNKNOWN
Classifier: Programming Language :: Python :: 3
Classifier: License :: OSI Approved :: BSD License
Classifier: Operating System :: OS Independent
License-File: LICENSE.txt
Requires-Dist: numpy
Requires-Dist: vector
